roboticspy/__init__.py
roboticspy/_version.py
roboticspy/tests/__init__.py
roboticspy/tests/conftest.py
roboticspy/tests/test_examples.py
roboticspy-0.0.1.dist-info/AUTHORS.rst
roboticspy-0.0.1.dist-info/LICENSE
roboticspy-0.0.1.dist-info/METADATA
roboticspy-0.0.1.dist-info/WHEEL
roboticspy-0.0.1.dist-info/top_level.txt
roboticspy-0.0.1.dist-info/RECORD
