Metadata-Version: 2.1
Name: roboticspy
Version: 0.0.1
Summary: Python package for doing science.
Home-page: https://github.com/davidcmccoll/roboticspy
Author: roboticspy
Author-email: davidcmccoll@gmail.com
License: BSD (3-clause)
Platform: UNKNOWN
Classifier: Development Status :: 2 - Pre-Alpha
Classifier: Natural Language :: English
Classifier: Programming Language :: Python :: 3
Requires-Python: >=3.9
License-File: LICENSE
License-File: AUTHORS.rst
